groupdocs_conversion_cloud/__init__.py
groupdocs_conversion_cloud/api_client.py
groupdocs_conversion_cloud/api_exception.py
groupdocs_conversion_cloud/auth.py
groupdocs_conversion_cloud/configuration.py
groupdocs_conversion_cloud/rest.py
groupdocs_conversion_cloud/apis/__init__.py
groupdocs_conversion_cloud/apis/async_api.py
groupdocs_conversion_cloud/apis/convert_api.py
groupdocs_conversion_cloud/apis/file_api.py
groupdocs_conversion_cloud/apis/folder_api.py
groupdocs_conversion_cloud/apis/info_api.py
groupdocs_conversion_cloud/apis/license_api.py
groupdocs_conversion_cloud/apis/storage_api.py
groupdocs_conversion_cloud/models/__init__.py
groupdocs_conversion_cloud/models/api_error.py
groupdocs_conversion_cloud/models/api_error_response.py
groupdocs_conversion_cloud/models/bmp_convert_options.py
groupdocs_conversion_cloud/models/cad_load_options.py
groupdocs_conversion_cloud/models/compression_load_options.py
groupdocs_conversion_cloud/models/consumption_result.py
groupdocs_conversion_cloud/models/convert_options.py
groupdocs_conversion_cloud/models/convert_settings.py
groupdocs_conversion_cloud/models/csv_load_options.py
groupdocs_conversion_cloud/models/database_load_options.py
groupdocs_conversion_cloud/models/dcm_convert_options.py
groupdocs_conversion_cloud/models/diagram_load_options.py
groupdocs_conversion_cloud/models/disc_usage.py
groupdocs_conversion_cloud/models/djvu_convert_options.py
groupdocs_conversion_cloud/models/dng_convert_options.py
groupdocs_conversion_cloud/models/doc_convert_options.py
groupdocs_conversion_cloud/models/docm_convert_options.py
groupdocs_conversion_cloud/models/document_metadata.py
groupdocs_conversion_cloud/models/docx_convert_options.py
groupdocs_conversion_cloud/models/dot_convert_options.py
groupdocs_conversion_cloud/models/dotm_convert_options.py
groupdocs_conversion_cloud/models/dotx_convert_options.py
groupdocs_conversion_cloud/models/e_book_convert_options.py
groupdocs_conversion_cloud/models/e_book_load_options.py
groupdocs_conversion_cloud-25.10.dist-info/licenses/LICENSE
groupdocs_conversion_cloud-25.10.dist-info/METADATA
groupdocs_conversion_cloud-25.10.dist-info/WHEEL
groupdocs_conversion_cloud-25.10.dist-info/top_level.txt
groupdocs_conversion_cloud-25.10.dist-info/RECORD
